tututools/__init__.py
tututools/plotgui.py
tututools/plts_tools.py
tututools/utils.py
tututools-0.0.3.1.dist-info/METADATA
tututools-0.0.3.1.dist-info/WHEEL
tututools-0.0.3.1.dist-info/entry_points.txt
tututools-0.0.3.1.dist-info/top_level.txt
tututools-0.0.3.1.dist-info/RECORD
