Metadata-Version: 2.1
Name: tututools
Version: 0.0.3.1
Summary: Some dev tools
Home-page: http://www.jintupersonal.com/
Author: JintuZheng
Author-email: jintuzheng@outlook.com
License: MIT
Keywords: tututools
Platform: UNKNOWN
Requires-Python: >=3.6
Requires-Dist: numpy
Requires-Dist: matplotlib
Requires-Dist: opencv-python
Requires-Dist: scikit-image
Requires-Dist: scipy
Requires-Dist: pyzmq
